ad_interface_functions/__init__.py
ad_interface_functions/udp_export.py
ad_interface_functions/udp_import.py
ad_interface_functions/zmq_export.py
ad_interface_functions/zmq_import.py
ad_interface_functions/zmq_import_poll.py
ad_interface_functions-0.21.dist-info/LICENSE
ad_interface_functions-0.21.dist-info/METADATA
ad_interface_functions-0.21.dist-info/WHEEL
ad_interface_functions-0.21.dist-info/top_level.txt
ad_interface_functions-0.21.dist-info/RECORD
