Metadata-Version: 2.1
Name: ad-interface-functions
Version: 0.21
Summary: Interface functions used in the autonomous driving stack at TUM/FTM
Home-page: https://www.ftm.mw.tum.de/en/main-research/vehicle-dynamics-and-control-systems/roborace-autonomous-motorsport/
Author: Alexander Heilmeier, Tim Stahl
Author-email: alexander.heilmeier@tum.de, stahl@ftm.mw.tum.de
License: UNKNOWN
Platform: UNKNOWN
Classifier: Programming Language :: Python :: 3
Classifier: Programming Language :: Python :: 3.5
Classifier: Programming Language :: Python :: 3.6
Classifier: Programming Language :: Python :: 3.7
Classifier: Programming Language :: Python :: 3.8
Classifier: License :: OSI Approved :: GNU Lesser General Public License v3 (LGPLv3)
Classifier: Operating System :: OS Independent
Requires-Dist: pyzmq (==19.0.2)
